{
  "Brazil": "BR",
  "United States": "US",
  "United Kingdom": "GB",
  "Canada": "CA",
  "Australia": "AU",
  "Germany": "DE",
  "France": "FR",
  "Italy": "IT",
  "Spain": "ES",
  "Japan": "JP",
  "China": "CN",
  "India": "IN",
  "Mexico": "MX",
  "Argentina": "AR",
  "Chile": "CL",
  "Colombia": "CO",
  "Peru": "PE",
  "Venezuela": "VE",
  "Ecuador": "EC",
  "Uruguay": "UY",
  "Paraguay": "PY",
  "Bolivia": "BO",
  "Guyana": "GY",
  "Suriname": "SR",
  "French Guiana": "GF",
  "Netherlands": "NL",
  "Belgium": "BE",
  "Switzerland": "CH",
  "Austria": "AT",
  "Sweden": "SE",
  "Norway": "NO",
  "Denmark": "DK",
  "Finland": "FI",
  "Poland": "PL",
  "Czech Republic": "CZ",
  "Hungary": "HU",
  "Romania": "RO",
  "Bulgaria": "BG",
  "Croatia": "HR",
  "Serbia": "RS",
  "Slovenia": "SI",
  "Slovakia": "SK",
  "Lithuania": "LT",
  "Latvia": "LV",
  "Estonia": "EE",
  "Portugal": "PT",
  "Greece": "GR",
  "Turkey": "TR",
  "Russia": "RU",
  "Ukraine": "UA",
  "Belarus": "BY",
  "Moldova": "MD",
  "South Africa": "ZA",
  "Egypt": "EG",
  "Nigeria": "NG",
  "Kenya": "KE",
  "Morocco": "MA",
  "Algeria": "DZ",
  "Tunisia": "TN",
  "Libya": "LY",
  "Sudan": "SD",
  "Ethiopia": "ET",
  "Ghana": "GH",
  "Ivory Coast": "CI",
  "Senegal": "SN",
  "Mali": "ML",
  "Burkina Faso": "BF",
  "Niger": "NE",
  "Chad": "TD",
  "Cameroon": "CM",
  "Central African Republic": "CF",
  "Democratic Republic of the Congo": "CD",
  "Republic of the Congo": "CG",
  "Gabon": "GA",
  "Equatorial Guinea": "GQ",
  "São Tomé and Príncipe": "ST",
  "Angola": "AO",
  "Zambia": "ZM",
  "Zimbabwe": "ZW",
  "Botswana": "BW",
  "Namibia": "NA",
  "Lesotho": "LS",
  "Swaziland": "SZ",
  "Madagascar": "MG",
  "Mauritius": "MU",
  "Seychelles": "SC",
  "Comoros": "KM",
  "Djibouti": "DJ",
  "Somalia": "SO",
  "Eritrea": "ER",
  "Tanzania": "TZ",
  "Uganda": "UG",
  "Rwanda": "RW",
  "Burundi": "BI",
  "Malawi": "MW",
  "Mozambique": "MZ",
  "Saudi Arabia": "SA",
  "United Arab Emirates": "AE",
  "Qatar": "QA",
  "Kuwait": "KW",
  "Bahrain": "BH",
  "Oman": "OM",
  "Yemen": "YE",
  "Iraq": "IQ",
  "Iran": "IR",
  "Afghanistan": "AF",
  "Pakistan": "PK",
  "Bangladesh": "BD",
  "Sri Lanka": "LK",
  "Maldives": "MV",
  "Nepal": "NP",
  "Bhutan": "BT",
  "Myanmar": "MM",
  "Thailand": "TH",
  "Laos": "LA",
  "Cambodia": "KH",
  "Vietnam": "VN",
  "Malaysia": "MY",
  "Singapore": "SG",
  "Indonesia": "ID",
  "Philippines": "PH",
  "Brunei": "BN",
  "East Timor": "TL",
  "Papua New Guinea": "PG",
  "Solomon Islands": "SB",
  "Vanuatu": "VU",
  "Fiji": "FJ",
  "Tonga": "TO",
  "Samoa": "WS",
  "Kiribati": "KI",
  "Tuvalu": "TV",
  "Nauru": "NR",
  "Palau": "PW",
  "Marshall Islands": "MH",
  "Micronesia": "FM",
  "New Zealand": "NZ",
  "Israel": "IL",
  "Palestine": "PS",
  "Jordan": "JO",
  "Lebanon": "LB",
  "Syria": "SY",
  "Cyprus": "CY",
  "Georgia": "GE",
  "Armenia": "AM",
  "Azerbaijan": "AZ",
  "Kazakhstan": "KZ",
  "Uzbekistan": "UZ",
  "Turkmenistan": "TM",
  "Tajikistan": "TJ",
  "Kyrgyzstan": "KG",
  "Mongolia": "MN",
  "North Korea": "KP",
  "South Korea": "KR",
  "Taiwan": "TW",
  "Hong Kong": "HK",
  "Macau": "MO",
  "BRA": "BR",
  "USA": "US",
  "GBR": "GB",
  "CAN": "CA",
  "AUS": "AU",
  "DEU": "DE",
  "FRA": "FR",
  "ITA": "IT",
  "ESP": "ES",
  "JPN": "JP",
  "CHN": "CN",
  "IND": "IN",
  "MEX": "MX",
  "ARG": "AR",
  "CHL": "CL",
  "COL": "CO",
  "PER": "PE",
  "VEN": "VE",
  "ECU": "EC",
  "URY": "UY",
  "PRY": "PY",
  "BOL": "BO",
  "GUY": "GY",
  "SUR": "SR",
  "NLD": "NL",
  "BEL": "BE",
  "CHE": "CH",
  "AUT": "AT",
  "SWE": "SE",
  "NOR": "NO",
  "DNK": "DK",
  "FIN": "FI",
  "POL": "PL",
  "CZE": "CZ",
  "HUN": "HU",
  "ROU": "RO",
  "BGR": "BG",
  "HRV": "HR",
  "SRB": "RS",
  "SVN": "SI",
  "SVK": "SK",
  "LTU": "LT",
  "LVA": "LV",
  "EST": "EE",
  "PRT": "PT",
  "GRC": "GR",
  "TUR": "TR",
  "RUS": "RU",
  "UKR": "UA",
  "BLR": "BY",
  "MDA": "MD",
  "ZAF": "ZA",
  "EGY": "EG",
  "NGA": "NG",
  "KEN": "KE",
  "MAR": "MA",
  "DZA": "DZ",
  "TUN": "TN",
  "LBY": "LY",
  "SDN": "SD",
  "ETH": "ET",
  "GHA": "GH",
  "CIV": "CI",
  "SEN": "SN",
  "MLI": "ML",
  "BFA": "BF",
  "NER": "NE",
  "TCD": "TD",
  "CMR": "CM",
  "CAF": "CF",
  "COD": "CD",
  "COG": "CG",
  "GAB": "GA",
  "GNQ": "GQ",
  "STP": "ST",
  "AGO": "AO",
  "ZMB": "ZM",
  "ZWE": "ZW",
  "BWA": "BW",
  "NAM": "NA",
  "LSO": "LS",
  "SWZ": "SZ",
  "MDG": "MG",
  "MUS": "MU",
  "SYC": "SC",
  "COM": "KM",
  "DJI": "DJ",
  "SOM": "SO",
  "ERI": "ER",
  "TZA": "TZ",
  "UGA": "UG",
  "RWA": "RW",
  "BDI": "BI",
  "MWI": "MW",
  "MOZ": "MZ",
  "SAU": "SA",
  "ARE": "AE",
  "QAT": "QA",
  "KWT": "KW",
  "BHR": "BH",
  "OMN": "OM",
  "YEM": "YE",
  "IRQ": "IQ",
  "IRN": "IR",
  "AFG": "AF",
  "PAK": "PK",
  "BGD": "BD",
  "LKA": "LK",
  "MDV": "MV",
  "NPL": "NP",
  "BTN": "BT",
  "MMR": "MM",
  "THA": "TH",
  "LAO": "LA",
  "KHM": "KH",
  "VNM": "VN",
  "MYS": "MY",
  "SGP": "SG",
  "IDN": "ID",
  "PHL": "PH",
  "BRN": "BN",
  "TLS": "TL",
  "PNG": "PG",
  "SLB": "SB",
  "VUT": "VU",
  "FJI": "FJ",
  "TON": "TO",
  "WSM": "WS",
  "KIR": "KI",
  "TUV": "TV",
  "NRU": "NR",
  "PLW": "PW",
  "MHL": "MH",
  "FSM": "FM",
  "NZL": "NZ",
  "ISR": "IL",
  "PSE": "PS",
  "JOR": "JO",
  "LBN": "LB",
  "SYR": "SY",
  "CYP": "CY",
  "GEO": "GE",
  "ARM": "AM",
  "AZE": "AZ",
  "KAZ": "KZ",
  "UZB": "UZ",
  "TKM": "TM",
  "TJK": "TJ",
  "KGZ": "KG",
  "MNG": "MN",
  "PRK": "KP",
  "KOR": "KR",
  "TWN": "TW",
  "HKG": "HK",
  "MAC": "MO"
}
